odoo/addons/hr_expense_sheet_payment_state/README.rst
odoo/addons/hr_expense_sheet_payment_state/__init__.py
odoo/addons/hr_expense_sheet_payment_state/__manifest__.py
odoo/addons/hr_expense_sheet_payment_state/i18n/hr_expense_sheet_payment_state.pot
odoo/addons/hr_expense_sheet_payment_state/i18n/it.po
odoo/addons/hr_expense_sheet_payment_state/models/__init__.py
odoo/addons/hr_expense_sheet_payment_state/models/account_move.py
odoo/addons/hr_expense_sheet_payment_state/models/hr_expense.py
odoo/addons/hr_expense_sheet_payment_state/readme/CONTRIBUTORS.rst
odoo/addons/hr_expense_sheet_payment_state/readme/DESCRIPTION.rst
odoo/addons/hr_expense_sheet_payment_state/readme/USAGE.rst
odoo/addons/hr_expense_sheet_payment_state/static/description/icon.png
odoo/addons/hr_expense_sheet_payment_state/static/description/index.html
odoo/addons/hr_expense_sheet_payment_state/tests/__init__.py
odoo/addons/hr_expense_sheet_payment_state/tests/test_expense_sheet_payment_state.py
odoo/addons/hr_expense_sheet_payment_state/views/hr_expense_views.xml
odoo14_addon_hr_expense_sheet_payment_state-14.0.1.0.1.dist-info/METADATA
odoo14_addon_hr_expense_sheet_payment_state-14.0.1.0.1.dist-info/WHEEL
odoo14_addon_hr_expense_sheet_payment_state-14.0.1.0.1.dist-info/top_level.txt
odoo14_addon_hr_expense_sheet_payment_state-14.0.1.0.1.dist-info/RECORD
