Metadata-Version: 2.1
Name: odoo14-addon-hr-expense-sheet-payment-state
Version: 14.0.1.0.1
Summary: Backport of the Payment Status (payment_state field) in Expense Report which is introduced in Odoo Community Version 15.0
Home-page: https://github.com/OCA/hr-expense
Author: Odoo SA, Odoo Community Association (OCA), Camptocamp
Author-email: support@odoo-community.org
License: LGPL-3
Platform: UNKNOWN
Classifier: Programming Language :: Python
Classifier: Framework :: Odoo
Classifier: Framework :: Odoo :: 14.0
Classifier: License :: OSI Approved :: GNU Lesser General Public License v3 (LGPLv3)
Requires-Python: >=3.6
Requires-Dist: odoo <14.1dev,>=14.0a
